[
    {
        "Name": "AGLD",
        "ID": "001",
        "Logo": "../assets/AG_logo.png",
        "Location": "",
        "Properties": {
            "BarID": "",
            "BarSerial": "",
            "VaultLocation": "",
            "Weight": "",
            "Purity": "",
            "DateRec": "",
            "DateProc": "",
            "Supplier": ""
        }
    },
    {
        "Name": "Tastee Toasters",
        "ID":"002",
        "Logo": "../assets/icon_logout.png",
        "Location": "",
        "Properties": {
            "Weight": "",
            "Color": "",
            "NumSlices": "",
            "Height": "",
            "Width": "",
            "Condition": "",
            "Style": "",
            "XtraProp": "testerExtra"
        }
    }
]